sixer.py
sixer-1.6.1.dist-info/COPYING
sixer-1.6.1.dist-info/METADATA
sixer-1.6.1.dist-info/WHEEL
sixer-1.6.1.dist-info/entry_points.txt
sixer-1.6.1.dist-info/top_level.txt
sixer-1.6.1.dist-info/RECORD
