Metadata-Version: 2.1
Name: sixer
Version: 1.6.1
Summary: Add Python 3 support to Python 2 applications using the six module.
Home-page: https://github.com/vstinner/sixer
Author: Victor Stinner
Author-email: victor.stinner@gmail.com
License: Apache License 2.0
Platform: UNKNOWN
Classifier: Programming Language :: Python
Classifier: Programming Language :: Python :: 3
Classifier: License :: OSI Approved :: Apache Software License
